libsentencepiece.0.dylib
libsentencepiece.0.0.0.dylib
libsentencepiece.dylib
pygemma.cpython-311-darwin.so
pygemma.dylibs/libsentencepiece.0.0.0.dylib
pygemma-0.1.3.post3.dist-info/RECORD
pygemma-0.1.3.post3.dist-info/LICENSE
pygemma-0.1.3.post3.dist-info/WHEEL
pygemma-0.1.3.post3.dist-info/top_level.txt
pygemma-0.1.3.post3.dist-info/METADATA
