Metadata-Version: 2.1
Name: pygemma
Version: 0.1.3.post3
Summary: A Python package with a C++ backend using gemma.cpp
Author: Nam Tran
Author-email: namtran.ase@gmail.com
Classifier: Programming Language :: Python :: 3
Classifier: License :: OSI Approved :: MIT License
Classifier: Operating System :: OS Independent
Requires-Python: >=3.8
License-File: LICENSE
